{"version":2,"kind":"Article","sha256":"34d674d5f5197f0d68870460e782a737dcbaba7c32975eb70aa5aa48eeb59e0f","slug":"conclusion","location":"/conclusion.md","dependencies":[],"frontmatter":{"title":"Conclusions","content_includes_title":false,"authors":[{"nameParsed":{"literal":"Max Ghenis","given":"Max","family":"Ghenis"},"name":"Max Ghenis","email":"max@policyengine.org","id":"contributors-myst-generated-uid-0","corresponding":true}],"github":"https://github.com/maxghenis/yankee-stadium-beer-price-controls","keywords":["economics","sports","price controls","externalities","alcohol policy","pigouvian tax"],"copyright":"2025","numbering":{"title":{"offset":1}},"edit_url":"https://github.com/maxghenis/yankee-stadium-beer-price-controls/blob/master/docs/conclusion.md","exports":[{"format":"md","filename":"conclusion.md","url":"/conclusion-967b2d87739f5e368f759ff365d04816.md"}]},"mdast":{"type":"root","children":[{"type":"block","children":[{"type":"heading","depth":2,"position":{"start":{"line":3,"column":1},"end":{"line":3,"column":1}},"children":[{"type":"text","value":"Key Findings","position":{"start":{"line":3,"column":1},"end":{"line":3,"column":1}},"key":"mih3nIWZjI"}],"identifier":"key-findings","label":"Key Findings","html_id":"key-findings","implicit":true,"key":"evzzsX2Vth"},{"type":"heading","depth":3,"position":{"start":{"line":5,"column":1},"end":{"line":5,"column":1}},"children":[{"type":"text","value":"1. Observed Prices Are Profit-Maximizing","position":{"start":{"line":5,"column":1},"end":{"line":5,"column":1}},"key":"h0PwYNHQhR"}],"identifier":"id-1-observed-prices-are-profit-maximizing","label":"1. Observed Prices Are Profit-Maximizing","html_id":"id-1-observed-prices-are-profit-maximizing","implicit":true,"key":"ILwI2AxpX0"},{"type":"paragraph","position":{"start":{"line":7,"column":1},"end":{"line":7,"column":1}},"children":[{"type":"text","value":"Stadium beer at ","position":{"start":{"line":7,"column":1},"end":{"line":7,"column":1}},"key":"YlOYm3Jc65"},{"type":"inlineMath","value":"12.50 is approximately profit-maximizing (","position":{"start":{"line":7,"column":1},"end":{"line":7,"column":1}},"html":"<span class=\"katex\"><span class=\"katex-mathml\"><math xmlns=\"http://www.w3.org/1998/Math/MathML\"><semantics><mrow><mn>12.50</mn><mi>i</mi><mi>s</mi><mi>a</mi><mi>p</mi><mi>p</mi><mi>r</mi><mi>o</mi><mi>x</mi><mi>i</mi><mi>m</mi><mi>a</mi><mi>t</mi><mi>e</mi><mi>l</mi><mi>y</mi><mi>p</mi><mi>r</mi><mi>o</mi><mi>f</mi><mi>i</mi><mi>t</mi><mo>−</mo><mi>m</mi><mi>a</mi><mi>x</mi><mi>i</mi><mi>m</mi><mi>i</mi><mi>z</mi><mi>i</mi><mi>n</mi><mi>g</mi><mo stretchy=\"false\">(</mo></mrow><annotation encoding=\"application/x-tex\">12.50 is approximately profit-maximizing (</annotation></semantics></math></span><span class=\"katex-html\" aria-hidden=\"true\"><span class=\"base\"><span class=\"strut\" style=\"height:0.8889em;vertical-align:-0.1944em;\"></span><span class=\"mord\">12.50</span><span class=\"mord mathnormal\">i</span><span class=\"mord mathnormal\">s</span><span class=\"mord mathnormal\">a</span><span class=\"mord mathnormal\">pp</span><span class=\"mord mathnormal\">ro</span><span class=\"mord mathnormal\">x</span><span class=\"mord mathnormal\">ima</span><span class=\"mord mathnormal\">t</span><span class=\"mord mathnormal\">e</span><span class=\"mord mathnormal\" style=\"margin-right:0.01968em;\">l</span><span class=\"mord mathnormal\" style=\"margin-right:0.03588em;\">y</span><span class=\"mord mathnormal\">p</span><span class=\"mord mathnormal\">ro</span><span class=\"mord mathnormal\" style=\"margin-right:0.10764em;\">f</span><span class=\"mord mathnormal\">i</span><span class=\"mord mathnormal\">t</span><span class=\"mspace\" style=\"margin-right:0.2222em;\"></span><span class=\"mbin\">−</span><span class=\"mspace\" style=\"margin-right:0.2222em;\"></span></span><span class=\"base\"><span class=\"strut\" style=\"height:1em;vertical-align:-0.25em;\"></span><span class=\"mord mathnormal\">ma</span><span class=\"mord mathnormal\">x</span><span class=\"mord mathnormal\">imi</span><span class=\"mord mathnormal\" style=\"margin-right:0.04398em;\">z</span><span class=\"mord mathnormal\">in</span><span class=\"mord mathnormal\" style=\"margin-right:0.03588em;\">g</span><span class=\"mopen\">(</span></span></span></span>","key":"kEmZexBeRs"},{"type":"text","value":"12.85 optimal) when accounting for:","position":{"start":{"line":7,"column":1},"end":{"line":7,"column":1}},"key":"Bi97nKy3Qq"}],"key":"vJyHqK8hs8"},{"type":"list","ordered":false,"spread":false,"position":{"start":{"line":8,"column":1},"end":{"line":11,"column":1}},"children":[{"type":"listItem","spread":true,"position":{"start":{"line":8,"column":1},"end":{"line":8,"column":1}},"children":[{"type":"text","value":"Taxes ($1.09/beer)","position":{"start":{"line":8,"column":1},"end":{"line":8,"column":1}},"key":"ygrIHLmmnf"}],"key":"lxAkD70Q59"},{"type":"listItem","spread":true,"position":{"start":{"line":9,"column":1},"end":{"line":9,"column":1}},"children":[{"type":"text","value":"Production costs ($5.00/beer)","position":{"start":{"line":9,"column":1},"end":{"line":9,"column":1}},"key":"PaptVLe6bO"}],"key":"azyxeVElUs"},{"type":"listItem","spread":true,"position":{"start":{"line":10,"column":1},"end":{"line":11,"column":1}},"children":[{"type":"strong","position":{"start":{"line":10,"column":1},"end":{"line":10,"column":1}},"children":[{"type":"text","value":"Internalized costs","position":{"start":{"line":10,"column":1},"end":{"line":10,"column":1}},"key":"GGKkkWOtzN"}],"key":"oIaN2JiO5Q"},{"type":"text","value":" (","position":{"start":{"line":10,"column":1},"end":{"line":10,"column":1}},"key":"cH8YVh74FX"},{"type":"inlineMath","value":"0.04-","position":{"start":{"line":10,"column":1},"end":{"line":10,"column":1}},"html":"<span class=\"katex\"><span class=\"katex-mathml\"><math xmlns=\"http://www.w3.org/1998/Math/MathML\"><semantics><mrow><mn>0.04</mn><mo>−</mo></mrow><annotation encoding=\"application/x-tex\">0.04-</annotation></semantics></math></span><span class=\"katex-html\" aria-hidden=\"true\"><span class=\"base\"><span class=\"strut\" style=\"height:0.7278em;vertical-align:-0.0833em;\"></span><span class=\"mord\">0.04</span><span class=\"mord\">−</span></span></span></span>","key":"n39nLo4OPu"},{"type":"text","value":"1.50/beer depending on volume)","position":{"start":{"line":10,"column":1},"end":{"line":10,"column":1}},"key":"klqq8Bpa18"}],"key":"WuAqA6XSxC"}],"key":"ymRfT2RX7u"},{"type":"heading","depth":3,"position":{"start":{"line":12,"column":1},"end":{"line":12,"column":1}},"children":[{"type":"text","value":"2. Stadiums Already Internalize Some Externalities","position":{"start":{"line":12,"column":1},"end":{"line":12,"column":1}},"key":"XYB77az49s"}],"identifier":"id-2-stadiums-already-internalize-some-externalities","label":"2. Stadiums Already Internalize Some Externalities","html_id":"id-2-stadiums-already-internalize-some-externalities","implicit":true,"key":"gtYiOzeMF7"},{"type":"paragraph","position":{"start":{"line":14,"column":1},"end":{"line":14,"column":1}},"children":[{"type":"text","value":"Crowd management, brand damage, and experience degradation are ","position":{"start":{"line":14,"column":1},"end":{"line":14,"column":1}},"key":"arAY8E6gVQ"},{"type":"strong","position":{"start":{"line":14,"column":1},"end":{"line":14,"column":1}},"children":[{"type":"text","value":"already priced in","position":{"start":{"line":14,"column":1},"end":{"line":14,"column":1}},"key":"j6OQwnTS9W"}],"key":"omHYxiW6Af"},{"type":"text","value":":","position":{"start":{"line":14,"column":1},"end":{"line":14,"column":1}},"key":"tNZBvzrhMf"}],"key":"jHAXqCfLFa"},{"type":"list","ordered":false,"spread":false,"position":{"start":{"line":15,"column":1},"end":{"line":18,"column":1}},"children":[{"type":"listItem","spread":true,"position":{"start":{"line":15,"column":1},"end":{"line":15,"column":1}},"children":[{"type":"text","value":"Convex cost function: ","position":{"start":{"line":15,"column":1},"end":{"line":15,"column":1}},"key":"iAWRhhu8OK"},{"type":"inlineMath","value":"C_{intern}(Q) = 250 \\cdot (Q/1000)^2","position":{"start":{"line":15,"column":1},"end":{"line":15,"column":1}},"html":"<span class=\"katex\"><span class=\"katex-mathml\"><math xmlns=\"http://www.w3.org/1998/Math/MathML\"><semantics><mrow><msub><mi>C</mi><mrow><mi>i</mi><mi>n</mi><mi>t</mi><mi>e</mi><mi>r</mi><mi>n</mi></mrow></msub><mo stretchy=\"false\">(</mo><mi>Q</mi><mo stretchy=\"false\">)</mo><mo>=</mo><mn>250</mn><mo>⋅</mo><mo stretchy=\"false\">(</mo><mi>Q</mi><mi mathvariant=\"normal\">/</mi><mn>1000</mn><msup><mo stretchy=\"false\">)</mo><mn>2</mn></msup></mrow><annotation encoding=\"application/x-tex\">C_{intern}(Q) = 250 \\cdot (Q/1000)^2</annotation></semantics></math></span><span class=\"katex-html\" aria-hidden=\"true\"><span class=\"base\"><span class=\"strut\" style=\"height:1em;vertical-align:-0.25em;\"></span><span class=\"mord\"><span class=\"mord mathnormal\" style=\"margin-right:0.07153em;\">C</span><span class=\"msupsub\"><span class=\"vlist-t vlist-t2\"><span class=\"vlist-r\"><span class=\"vlist\" style=\"height:0.3117em;\"><span style=\"top:-2.55em;margin-left:-0.0715em;margin-right:0.05em;\"><span class=\"pstrut\" style=\"height:2.7em;\"></span><span class=\"sizing reset-size6 size3 mtight\"><span class=\"mord mtight\"><span class=\"mord mathnormal mtight\">in</span><span class=\"mord mathnormal mtight\">t</span><span class=\"mord mathnormal mtight\" style=\"margin-right:0.02778em;\">er</span><span class=\"mord mathnormal mtight\">n</span></span></span></span></span><span class=\"vlist-s\">​</span></span><span class=\"vlist-r\"><span class=\"vlist\" style=\"height:0.15em;\"><span></span></span></span></span></span></span><span class=\"mopen\">(</span><span class=\"mord mathnormal\">Q</span><span class=\"mclose\">)</span><span class=\"mspace\" style=\"margin-right:0.2778em;\"></span><span class=\"mrel\">=</span><span class=\"mspace\" style=\"margin-right:0.2778em;\"></span></span><span class=\"base\"><span class=\"strut\" style=\"height:0.6444em;\"></span><span class=\"mord\">250</span><span class=\"mspace\" style=\"margin-right:0.2222em;\"></span><span class=\"mbin\">⋅</span><span class=\"mspace\" style=\"margin-right:0.2222em;\"></span></span><span class=\"base\"><span class=\"strut\" style=\"height:1.0641em;vertical-align:-0.25em;\"></span><span class=\"mopen\">(</span><span class=\"mord mathnormal\">Q</span><span class=\"mord\">/1000</span><span class=\"mclose\"><span class=\"mclose\">)</span><span class=\"msupsub\"><span class=\"vlist-t\"><span class=\"vlist-r\"><span class=\"vlist\" style=\"height:0.8141em;\"><span style=\"top:-3.063em;margin-right:0.05em;\"><span class=\"pstrut\" style=\"height:2.7em;\"></span><span class=\"sizing reset-size6 size3 mtight\"><span class=\"mord mtight\">2</span></span></span></span></span></span></span></span></span></span></span>","key":"QqWhdEHie8"}],"key":"P4DbBgQDKd"},{"type":"listItem","spread":true,"position":{"start":{"line":16,"column":1},"end":{"line":16,"column":1}},"children":[{"type":"text","value":"At low prices ($5-7): Internalized costs become prohibitively high","position":{"start":{"line":16,"column":1},"end":{"line":16,"column":1}},"key":"bE2AoTly2n"}],"key":"BBJfhSlkju"},{"type":"listItem","spread":true,"position":{"start":{"line":17,"column":1},"end":{"line":18,"column":1}},"children":[{"type":"text","value":"This explains why stadiums don’t sell cheap beer despite apparent profit potential","position":{"start":{"line":17,"column":1},"end":{"line":17,"column":1}},"key":"IuR8EhkEVT"}],"key":"Op7nTPsHHs"}],"key":"eX1aAansfd"},{"type":"heading","depth":3,"position":{"start":{"line":19,"column":1},"end":{"line":19,"column":1}},"children":[{"type":"text","value":"3. Significant External Costs Remain","position":{"start":{"line":19,"column":1},"end":{"line":19,"column":1}},"key":"XRdF8m2jGw"}],"identifier":"id-3-significant-external-costs-remain","label":"3. Significant External Costs Remain","html_id":"id-3-significant-external-costs-remain","implicit":true,"key":"Y6GimIAD1W"},{"type":"paragraph","position":{"start":{"line":21,"column":1},"end":{"line":21,"column":1}},"children":[{"type":"text","value":"Society bears ","position":{"start":{"line":21,"column":1},"end":{"line":21,"column":1}},"key":"KrEbCK1e6R"},{"type":"strong","position":{"start":{"line":21,"column":1},"end":{"line":21,"column":1}},"children":[{"type":"text","value":"$4.00/beer","position":{"start":{"line":21,"column":1},"end":{"line":21,"column":1}},"key":"t52Tx9sGGQ"}],"key":"nANVySP8g9"},{"type":"text","value":" in external costs:","position":{"start":{"line":21,"column":1},"end":{"line":21,"column":1}},"key":"dP1Cww4qh8"}],"key":"XVP8wXvLPj"},{"type":"list","ordered":false,"spread":false,"position":{"start":{"line":22,"column":1},"end":{"line":24,"column":1}},"children":[{"type":"listItem","spread":true,"position":{"start":{"line":22,"column":1},"end":{"line":22,"column":1}},"children":[{"type":"text","value":"Crime & violence: $2.50","position":{"start":{"line":22,"column":1},"end":{"line":22,"column":1}},"key":"bVdhNxNV4L"}],"key":"UIBz9lxiS5"},{"type":"listItem","spread":true,"position":{"start":{"line":23,"column":1},"end":{"line":24,"column":1}},"children":[{"type":"text","value":"Public health: $1.50","position":{"start":{"line":23,"column":1},"end":{"line":23,"column":1}},"key":"h8v0zOyX2Y"}],"key":"sOXmJCfGID"}],"key":"prn0xUWVAo"},{"type":"paragraph","position":{"start":{"line":25,"column":1},"end":{"line":25,"column":1}},"children":[{"type":"text","value":"Current taxes ($1.09) cover only ","position":{"start":{"line":25,"column":1},"end":{"line":25,"column":1}},"key":"I2Do85eJcc"},{"type":"strong","position":{"start":{"line":25,"column":1},"end":{"line":25,"column":1}},"children":[{"type":"text","value":"27%","position":{"start":{"line":25,"column":1},"end":{"line":25,"column":1}},"key":"TFJhOD6Lkh"}],"key":"yLwWtV9Eys"},{"type":"text","value":" of these costs.","position":{"start":{"line":25,"column":1},"end":{"line":25,"column":1}},"key":"TTQ0RDWvvT"}],"key":"KAyLiIAF9U"},{"type":"paragraph","position":{"start":{"line":27,"column":1},"end":{"line":27,"column":1}},"children":[{"type":"strong","position":{"start":{"line":27,"column":1},"end":{"line":27,"column":1}},"children":[{"type":"text","value":"Pigouvian tax gap: $2.91/beer","position":{"start":{"line":27,"column":1},"end":{"line":27,"column":1}},"key":"tiw2fOO6Jj"}],"key":"oPU7wNqPq8"}],"key":"Ng03RQGZDn"},{"type":"heading","depth":3,"position":{"start":{"line":29,"column":1},"end":{"line":29,"column":1}},"children":[{"type":"text","value":"4. Price Ceiling ($7) Has Mixed Effects","position":{"start":{"line":29,"column":1},"end":{"line":29,"column":1}},"key":"pfEf4RCbH2"}],"identifier":"id-4-price-ceiling-7-has-mixed-effects","label":"4. Price Ceiling ($7) Has Mixed Effects","html_id":"id-4-price-ceiling-7-has-mixed-effects","implicit":true,"key":"QIKN7YT9tc"},{"type":"paragraph","position":{"start":{"line":31,"column":1},"end":{"line":31,"column":1}},"children":[{"type":"strong","position":{"start":{"line":31,"column":1},"end":{"line":31,"column":1}},"children":[{"type":"text","value":"Pros:","position":{"start":{"line":31,"column":1},"end":{"line":31,"column":1}},"key":"ETl3NMiNzg"}],"key":"qbqUuRBQjr"}],"key":"bSSTUFKwnE"},{"type":"list","ordered":false,"spread":false,"position":{"start":{"line":32,"column":1},"end":{"line":34,"column":1}},"children":[{"type":"listItem","spread":true,"position":{"start":{"line":32,"column":1},"end":{"line":32,"column":1}},"children":[{"type":"text","value":"Consumer surplus: +$543M/season","position":{"start":{"line":32,"column":1},"end":{"line":32,"column":1}},"key":"w9ZeaH0U4e"}],"key":"P8rEC7BNhm"},{"type":"listItem","spread":true,"position":{"start":{"line":33,"column":1},"end":{"line":34,"column":1}},"children":[{"type":"text","value":"More affordable access","position":{"start":{"line":33,"column":1},"end":{"line":33,"column":1}},"key":"eeuAd8KgVT"}],"key":"GM2bAlilzk"}],"key":"xZzeCH17Ro"},{"type":"paragraph","position":{"start":{"line":35,"column":1},"end":{"line":35,"column":1}},"children":[{"type":"strong","position":{"start":{"line":35,"column":1},"end":{"line":35,"column":1}},"children":[{"type":"text","value":"Cons:","position":{"start":{"line":35,"column":1},"end":{"line":35,"column":1}},"key":"vosI8mbFfY"}],"key":"lS6IpppkS8"}],"key":"Q4uOpskizC"},{"type":"list","ordered":false,"spread":false,"position":{"start":{"line":36,"column":1},"end":{"line":39,"column":1}},"children":[{"type":"listItem","spread":true,"position":{"start":{"line":36,"column":1},"end":{"line":36,"column":1}},"children":[{"type":"text","value":"Stadium profit: -$151M/season","position":{"start":{"line":36,"column":1},"end":{"line":36,"column":1}},"key":"FZQLtP5tSd"}],"key":"hg4ncpfYj9"},{"type":"listItem","spread":true,"position":{"start":{"line":37,"column":1},"end":{"line":37,"column":1}},"children":[{"type":"text","value":"Externality costs: +$12.4M/season","position":{"start":{"line":37,"column":1},"end":{"line":37,"column":1}},"key":"uonEDeMalg"}],"key":"xzrCCHz4SF"},{"type":"listItem","spread":true,"position":{"start":{"line":38,"column":1},"end":{"line":39,"column":1}},"children":[{"type":"text","value":"May face legal/constitutional challenges","position":{"start":{"line":38,"column":1},"end":{"line":38,"column":1}},"key":"oIfuFheTKU"}],"key":"zGJwAmelxr"}],"key":"fmBX7NDObO"},{"type":"paragraph","position":{"start":{"line":40,"column":1},"end":{"line":40,"column":1}},"children":[{"type":"strong","position":{"start":{"line":40,"column":1},"end":{"line":40,"column":1}},"children":[{"type":"text","value":"Net:","position":{"start":{"line":40,"column":1},"end":{"line":40,"column":1}},"key":"Bp7ih0c6QP"}],"key":"V45NqJ1iHw"},{"type":"text","value":" Positive social welfare (+$373M) but distributional concerns.","position":{"start":{"line":40,"column":1},"end":{"line":40,"column":1}},"key":"hJ6CdwMoHS"}],"key":"XgT0hRJWHr"},{"type":"heading","depth":3,"position":{"start":{"line":42,"column":1},"end":{"line":42,"column":1}},"children":[{"type":"text","value":"5. Pigouvian Tax is More Efficient","position":{"start":{"line":42,"column":1},"end":{"line":42,"column":1}},"key":"weNIfbfuBr"}],"identifier":"id-5-pigouvian-tax-is-more-efficient","label":"5. Pigouvian Tax is More Efficient","html_id":"id-5-pigouvian-tax-is-more-efficient","implicit":true,"key":"zU8HpJhvw1"},{"type":"paragraph","position":{"start":{"line":44,"column":1},"end":{"line":44,"column":1}},"children":[{"type":"text","value":"Adding $2.91/beer tax:","position":{"start":{"line":44,"column":1},"end":{"line":44,"column":1}},"key":"k6ywdTEwXO"}],"key":"UEEsadEpIg"},{"type":"list","ordered":false,"spread":false,"position":{"start":{"line":45,"column":1},"end":{"line":50,"column":1}},"children":[{"type":"listItem","spread":true,"position":{"start":{"line":45,"column":1},"end":{"line":45,"column":1}},"children":[{"type":"text","value":"✓ Internalizes external costs","position":{"start":{"line":45,"column":1},"end":{"line":45,"column":1}},"key":"qmqJLJRskv"}],"key":"ZQjau4grzm"},{"type":"listItem","spread":true,"position":{"start":{"line":46,"column":1},"end":{"line":46,"column":1}},"children":[{"type":"text","value":"✓ Raises $6.7M/season for affected communities","position":{"start":{"line":46,"column":1},"end":{"line":46,"column":1}},"key":"KdCDpPihXX"}],"key":"xdy2AJbcZO"},{"type":"listItem","spread":true,"position":{"start":{"line":47,"column":1},"end":{"line":47,"column":1}},"children":[{"type":"text","value":"✓ Reduces consumption to optimal level","position":{"start":{"line":47,"column":1},"end":{"line":47,"column":1}},"key":"LkwBamTNh3"}],"key":"imQsY0JuXA"},{"type":"listItem","spread":true,"position":{"start":{"line":48,"column":1},"end":{"line":48,"column":1}},"children":[{"type":"text","value":"✓ No deadweight loss (price = social MC)","position":{"start":{"line":48,"column":1},"end":{"line":48,"column":1}},"key":"mINppPYKSV"}],"key":"fkEQAFXhjw"},{"type":"listItem","spread":true,"position":{"start":{"line":49,"column":1},"end":{"line":50,"column":1}},"children":[{"type":"text","value":"✓ Economically efficient","position":{"start":{"line":49,"column":1},"end":{"line":49,"column":1}},"key":"lU93yQcUBv"}],"key":"dJQSmwu9xO"}],"key":"dynMM5b83r"},{"type":"paragraph","position":{"start":{"line":51,"column":1},"end":{"line":51,"column":1}},"children":[{"type":"strong","position":{"start":{"line":51,"column":1},"end":{"line":51,"column":1}},"children":[{"type":"text","value":"Recommended policy","position":{"start":{"line":51,"column":1},"end":{"line":51,"column":1}},"key":"ADs2qLbh9j"}],"key":"InkBbXKvvv"},{"type":"text","value":": Pigouvian tax over price controls.","position":{"start":{"line":51,"column":1},"end":{"line":51,"column":1}},"key":"Vwpx8An90u"}],"key":"HQjRugKQnv"},{"type":"heading","depth":2,"position":{"start":{"line":53,"column":1},"end":{"line":53,"column":1}},"children":[{"type":"text","value":"Policy Recommendations","position":{"start":{"line":53,"column":1},"end":{"line":53,"column":1}},"key":"D0cHFeAsf3"}],"identifier":"policy-recommendations","label":"Policy Recommendations","html_id":"policy-recommendations","implicit":true,"key":"FWMeC6EjVD"},{"type":"heading","depth":3,"position":{"start":{"line":55,"column":1},"end":{"line":55,"column":1}},"children":[{"type":"text","value":"Recommended: Pigouvian Tax","position":{"start":{"line":55,"column":1},"end":{"line":55,"column":1}},"key":"dCqJazq8Sw"}],"identifier":"recommended-pigouvian-tax","label":"Recommended: Pigouvian Tax","html_id":"recommended-pigouvian-tax","implicit":true,"key":"i5K4UyXfq2"},{"type":"paragraph","position":{"start":{"line":57,"column":1},"end":{"line":57,"column":1}},"children":[{"type":"strong","position":{"start":{"line":57,"column":1},"end":{"line":57,"column":1}},"children":[{"type":"text","value":"Implement $2.91/beer additional tax on stadium alcohol","position":{"start":{"line":57,"column":1},"end":{"line":57,"column":1}},"key":"v7NoZLmI2v"}],"key":"AJkSIYMUfP"}],"key":"WIHuMCFTRp"},{"type":"list","ordered":false,"spread":false,"position":{"start":{"line":59,"column":1},"end":{"line":63,"column":1}},"children":[{"type":"listItem","spread":true,"position":{"start":{"line":59,"column":1},"end":{"line":59,"column":1}},"children":[{"type":"text","value":"Consumer price: ","position":{"start":{"line":59,"column":1},"end":{"line":59,"column":1}},"key":"AfuWtAB6id"},{"type":"inlineMath","value":"12.50 → ","position":{"start":{"line":59,"column":1},"end":{"line":59,"column":1}},"html":"<span class=\"katex\"><span class=\"katex-mathml\"><math xmlns=\"http://www.w3.org/1998/Math/MathML\"><semantics><mrow><mn>12.50</mn><mo>→</mo></mrow><annotation encoding=\"application/x-tex\">12.50 → </annotation></semantics></math></span><span class=\"katex-html\" aria-hidden=\"true\"><span class=\"base\"><span class=\"strut\" style=\"height:0.6444em;\"></span><span class=\"mord\">12.50</span><span class=\"mspace\" style=\"margin-right:0.2778em;\"></span><span class=\"mrel\">→</span></span></span></span>","key":"OqXyTnfmqv"},{"type":"text","value":"15.41","position":{"start":{"line":59,"column":1},"end":{"line":59,"column":1}},"key":"n4jnpauznb"}],"key":"oPDxv6VoTW"},{"type":"listItem","spread":true,"position":{"start":{"line":60,"column":1},"end":{"line":60,"column":1}},"children":[{"type":"text","value":"Consumption: -29%","position":{"start":{"line":60,"column":1},"end":{"line":60,"column":1}},"key":"fbMBiETWKr"}],"key":"o6bo7WNsU7"},{"type":"listItem","spread":true,"position":{"start":{"line":61,"column":1},"end":{"line":61,"column":1}},"children":[{"type":"text","value":"Revenue: $6.7M/season","position":{"start":{"line":61,"column":1},"end":{"line":61,"column":1}},"key":"em3WyU8gB1"}],"key":"cGIRV7qDFh"},{"type":"listItem","spread":true,"position":{"start":{"line":62,"column":1},"end":{"line":63,"column":1}},"children":[{"type":"text","value":"Allocate to Bronx community, public health, police","position":{"start":{"line":62,"column":1},"end":{"line":62,"column":1}},"key":"BO5SquL1UQ"}],"key":"Z5VFOk33K1"}],"key":"Ad1Fl7O4kc"},{"type":"heading","depth":3,"position":{"start":{"line":64,"column":1},"end":{"line":64,"column":1}},"children":[{"type":"text","value":"Alternative: Moderate Hybrid","position":{"start":{"line":64,"column":1},"end":{"line":64,"column":1}},"key":"lziVWvpYJo"}],"identifier":"alternative-moderate-hybrid","label":"Alternative: Moderate Hybrid","html_id":"alternative-moderate-hybrid","implicit":true,"key":"rbw4jZf5Gs"},{"type":"paragraph","position":{"start":{"line":66,"column":1},"end":{"line":66,"column":1}},"children":[{"type":"strong","position":{"start":{"line":66,"column":1},"end":{"line":66,"column":1}},"children":[{"type":"text","value":"If political constraints:","position":{"start":{"line":66,"column":1},"end":{"line":66,"column":1}},"key":"fIvQFMc2VB"}],"key":"SQHdlvk9p5"}],"key":"LyoPUpGHOY"},{"type":"list","ordered":false,"spread":false,"position":{"start":{"line":67,"column":1},"end":{"line":70,"column":1}},"children":[{"type":"listItem","spread":true,"position":{"start":{"line":67,"column":1},"end":{"line":67,"column":1}},"children":[{"type":"text","value":"Moderate tax (+$1.50/beer)","position":{"start":{"line":67,"column":1},"end":{"line":67,"column":1}},"key":"hdJAToCfNI"}],"key":"yeNWJ0eWGf"},{"type":"listItem","spread":true,"position":{"start":{"line":68,"column":1},"end":{"line":68,"column":1}},"children":[{"type":"text","value":"Earlier sale cutoff (6th inning instead of 7th)","position":{"start":{"line":68,"column":1},"end":{"line":68,"column":1}},"key":"Sgo9ND9KvD"}],"key":"F3oUMx2z5w"},{"type":"listItem","spread":true,"position":{"start":{"line":69,"column":1},"end":{"line":70,"column":1}},"children":[{"type":"text","value":"Purchase limits (2 beers per transaction)","position":{"start":{"line":69,"column":1},"end":{"line":69,"column":1}},"key":"JhUbVWhTTZ"}],"key":"kuue01DLAX"}],"key":"GcPAzx1HxD"},{"type":"heading","depth":3,"position":{"start":{"line":71,"column":1},"end":{"line":71,"column":1}},"children":[{"type":"text","value":"Not Recommended: Price Ceiling","position":{"start":{"line":71,"column":1},"end":{"line":71,"column":1}},"key":"LhuBB4mLZF"}],"identifier":"not-recommended-price-ceiling","label":"Not Recommended: Price Ceiling","html_id":"not-recommended-price-ceiling","implicit":true,"key":"vwv51s7smZ"},{"type":"list","ordered":false,"spread":false,"position":{"start":{"line":73,"column":1},"end":{"line":77,"column":1}},"children":[{"type":"listItem","spread":true,"position":{"start":{"line":73,"column":1},"end":{"line":73,"column":1}},"children":[{"type":"text","value":"Large stadium revenue loss","position":{"start":{"line":73,"column":1},"end":{"line":73,"column":1}},"key":"aHZGvLkFnx"}],"key":"CzmkqAQ6aa"},{"type":"listItem","spread":true,"position":{"start":{"line":74,"column":1},"end":{"line":74,"column":1}},"children":[{"type":"text","value":"Increases externalities","position":{"start":{"line":74,"column":1},"end":{"line":74,"column":1}},"key":"kjKFSckurL"}],"key":"v6akodY75p"},{"type":"listItem","spread":true,"position":{"start":{"line":75,"column":1},"end":{"line":75,"column":1}},"children":[{"type":"text","value":"Potential legal challenges","position":{"start":{"line":75,"column":1},"end":{"line":75,"column":1}},"key":"BARXi2kzGq"}],"key":"MUO1opLWJ9"},{"type":"listItem","spread":true,"position":{"start":{"line":76,"column":1},"end":{"line":77,"column":1}},"children":[{"type":"text","value":"Less efficient than taxation","position":{"start":{"line":76,"column":1},"end":{"line":76,"column":1}},"key":"BvcFOappjN"}],"key":"m8lINKr1ea"}],"key":"ERIOUXH0Fj"},{"type":"heading","depth":2,"position":{"start":{"line":78,"column":1},"end":{"line":78,"column":1}},"children":[{"type":"text","value":"Broader Implications","position":{"start":{"line":78,"column":1},"end":{"line":78,"column":1}},"key":"HkWISbir0x"}],"identifier":"broader-implications","label":"Broader Implications","html_id":"broader-implications","implicit":true,"key":"zYPZ2QBMA2"},{"type":"heading","depth":3,"position":{"start":{"line":80,"column":1},"end":{"line":80,"column":1}},"children":[{"type":"text","value":"For Other Stadiums","position":{"start":{"line":80,"column":1},"end":{"line":80,"column":1}},"key":"L8xVBqHnmP"}],"identifier":"for-other-stadiums","label":"For Other Stadiums","html_id":"for-other-stadiums","implicit":true,"key":"lFzxyuVKc4"},{"type":"paragraph","position":{"start":{"line":82,"column":1},"end":{"line":82,"column":1}},"children":[{"type":"text","value":"This framework applies to all sports venues:","position":{"start":{"line":82,"column":1},"end":{"line":82,"column":1}},"key":"ZLhz5tgLgM"}],"key":"llONMCuxzS"},{"type":"list","ordered":false,"spread":false,"position":{"start":{"line":83,"column":1},"end":{"line":86,"column":1}},"children":[{"type":"listItem","spread":true,"position":{"start":{"line":83,"column":1},"end":{"line":83,"column":1}},"children":[{"type":"text","value":"NFL, NBA, NHL stadiums face similar trade-offs","position":{"start":{"line":83,"column":1},"end":{"line":83,"column":1}},"key":"myJYqkayvP"}],"key":"EQgdZ4XOCX"},{"type":"listItem","spread":true,"position":{"start":{"line":84,"column":1},"end":{"line":84,"column":1}},"children":[{"type":"text","value":"Internalized vs external costs distinction is general","position":{"start":{"line":84,"column":1},"end":{"line":84,"column":1}},"key":"z7eoW3CVs1"}],"key":"q6UmjiKgEj"},{"type":"listItem","spread":true,"position":{"start":{"line":85,"column":1},"end":{"line":86,"column":1}},"children":[{"type":"text","value":"Optimal taxation varies by local externality levels","position":{"start":{"line":85,"column":1},"end":{"line":85,"column":1}},"key":"BOpDXRNmsX"}],"key":"NltgZPdP32"}],"key":"U50Qb70Kv1"},{"type":"heading","depth":3,"position":{"start":{"line":87,"column":1},"end":{"line":87,"column":1}},"children":[{"type":"text","value":"For Alcohol Policy","position":{"start":{"line":87,"column":1},"end":{"line":87,"column":1}},"key":"o536dCk1TO"}],"identifier":"for-alcohol-policy","label":"For Alcohol Policy","html_id":"for-alcohol-policy","implicit":true,"key":"ScGu9zRfJq"},{"type":"paragraph","position":{"start":{"line":89,"column":1},"end":{"line":89,"column":1}},"children":[{"type":"strong","position":{"start":{"line":89,"column":1},"end":{"line":89,"column":1}},"children":[{"type":"text","value":"General principle","position":{"start":{"line":89,"column":1},"end":{"line":89,"column":1}},"key":"jU5U1p29YI"}],"key":"XkzsSprRIo"},{"type":"text","value":": Distinguish internalized from external costs.","position":{"start":{"line":89,"column":1},"end":{"line":89,"column":1}},"key":"Ux2dglNm5B"}],"key":"PXrfTTbYRy"},{"type":"paragraph","position":{"start":{"line":91,"column":1},"end":{"line":91,"column":1}},"children":[{"type":"text","value":"Monopolists (stadiums, bars, restaurants) internalize negative effects on their own customers.","position":{"start":{"line":91,"column":1},"end":{"line":91,"column":1}},"key":"WarTsKVKxM"}],"key":"OXK3O6HJDW"},{"type":"paragraph","position":{"start":{"line":93,"column":1},"end":{"line":93,"column":1}},"children":[{"type":"text","value":"Policy should target ","position":{"start":{"line":93,"column":1},"end":{"line":93,"column":1}},"key":"cHTDH3708K"},{"type":"strong","position":{"start":{"line":93,"column":1},"end":{"line":93,"column":1}},"children":[{"type":"text","value":"true external costs","position":{"start":{"line":93,"column":1},"end":{"line":93,"column":1}},"key":"aeukhB4guu"}],"key":"FzbeznPtAU"},{"type":"text","value":" (non-customers, public goods).","position":{"start":{"line":93,"column":1},"end":{"line":93,"column":1}},"key":"Gp3RgRLrqa"}],"key":"Wk3kGDJd1S"},{"type":"heading","depth":3,"position":{"start":{"line":95,"column":1},"end":{"line":95,"column":1}},"children":[{"type":"text","value":"For Price Control Theory","position":{"start":{"line":95,"column":1},"end":{"line":95,"column":1}},"key":"pPlWrQBgOr"}],"identifier":"for-price-control-theory","label":"For Price Control Theory","html_id":"for-price-control-theory","implicit":true,"key":"Mn9hP8SsxI"},{"type":"paragraph","position":{"start":{"line":97,"column":1},"end":{"line":97,"column":1}},"children":[{"type":"strong","position":{"start":{"line":97,"column":1},"end":{"line":97,"column":1}},"children":[{"type":"text","value":"Important insight","position":{"start":{"line":97,"column":1},"end":{"line":97,"column":1}},"key":"wiKcD36w3u"}],"key":"x09GSV6Qft"},{"type":"text","value":": Observed prices may reflect internalized externalities, not just production costs.","position":{"start":{"line":97,"column":1},"end":{"line":97,"column":1}},"key":"ZbXkhwIHGA"}],"key":"AeJ16tgVP3"},{"type":"paragraph","position":{"start":{"line":99,"column":1},"end":{"line":99,"column":1}},"children":[{"type":"text","value":"Standard models that ignore firm’s internalization of customer experience effects will mis-predict optimal prices.","position":{"start":{"line":99,"column":1},"end":{"line":99,"column":1}},"key":"k7D4UFm35O"}],"key":"fuqg0N4bof"},{"type":"heading","depth":2,"position":{"start":{"line":101,"column":1},"end":{"line":101,"column":1}},"children":[{"type":"text","value":"Limitations","position":{"start":{"line":101,"column":1},"end":{"line":101,"column":1}},"key":"Y739A5XYmP"}],"identifier":"limitations","label":"Limitations","html_id":"limitations","implicit":true,"key":"wZd0PUvPQV"},{"type":"list","ordered":true,"start":1,"spread":false,"position":{"start":{"line":103,"column":1},"end":{"line":108,"column":1}},"children":[{"type":"listItem","spread":true,"position":{"start":{"line":103,"column":1},"end":{"line":103,"column":1}},"children":[{"type":"strong","position":{"start":{"line":103,"column":1},"end":{"line":103,"column":1}},"children":[{"type":"text","value":"Static model","position":{"start":{"line":103,"column":1},"end":{"line":103,"column":1}},"key":"ZFp4SPH0NC"}],"key":"iDm6rta8jl"},{"type":"text","value":": Doesn’t capture long-run effects (season tickets, loyalty)","position":{"start":{"line":103,"column":1},"end":{"line":103,"column":1}},"key":"DDtSHzyvsn"}],"key":"Kgru16ec8J"},{"type":"listItem","spread":true,"position":{"start":{"line":104,"column":1},"end":{"line":104,"column":1}},"children":[{"type":"strong","position":{"start":{"line":104,"column":1},"end":{"line":104,"column":1}},"children":[{"type":"text","value":"Single representative consumer","position":{"start":{"line":104,"column":1},"end":{"line":104,"column":1}},"key":"j9a3wvkS0v"}],"key":"mHqqRjWdBe"},{"type":"text","value":": Ignores heterogeneity","position":{"start":{"line":104,"column":1},"end":{"line":104,"column":1}},"key":"wxKXme5Ckh"}],"key":"InS0AnOy5k"},{"type":"listItem","spread":true,"position":{"start":{"line":105,"column":1},"end":{"line":105,"column":1}},"children":[{"type":"strong","position":{"start":{"line":105,"column":1},"end":{"line":105,"column":1}},"children":[{"type":"text","value":"No substitution","position":{"start":{"line":105,"column":1},"end":{"line":105,"column":1}},"key":"buPaqskupB"}],"key":"WFdr0rNL04"},{"type":"text","value":": Doesn’t model pre-game drinking or smuggling","position":{"start":{"line":105,"column":1},"end":{"line":105,"column":1}},"key":"A1R0Xc8la2"}],"key":"Nqg2z7OzMv"},{"type":"listItem","spread":true,"position":{"start":{"line":106,"column":1},"end":{"line":106,"column":1}},"children":[{"type":"strong","position":{"start":{"line":106,"column":1},"end":{"line":106,"column":1}},"children":[{"type":"text","value":"Partial equilibrium","position":{"start":{"line":106,"column":1},"end":{"line":106,"column":1}},"key":"foHgORFXPm"}],"key":"dK3DZV9pCl"},{"type":"text","value":": No competition from other entertainment","position":{"start":{"line":106,"column":1},"end":{"line":106,"column":1}},"key":"JQEfqeHxzo"}],"key":"qKir9E9LHJ"},{"type":"listItem","spread":true,"position":{"start":{"line":107,"column":1},"end":{"line":108,"column":1}},"children":[{"type":"strong","position":{"start":{"line":107,"column":1},"end":{"line":107,"column":1}},"children":[{"type":"text","value":"Perfect enforcement","position":{"start":{"line":107,"column":1},"end":{"line":107,"column":1}},"key":"f3eYE3PKGr"}],"key":"yIdfM1anyo"},{"type":"text","value":": Assumes price controls fully enforced","position":{"start":{"line":107,"column":1},"end":{"line":107,"column":1}},"key":"J7izr8A64V"}],"key":"rajkXA5ONz"}],"key":"d6UPiOchAf"},{"type":"heading","depth":2,"position":{"start":{"line":109,"column":1},"end":{"line":109,"column":1}},"children":[{"type":"text","value":"Future Research","position":{"start":{"line":109,"column":1},"end":{"line":109,"column":1}},"key":"gU75AUTVKY"}],"identifier":"future-research","label":"Future Research","html_id":"future-research","implicit":true,"key":"hCaTjG6Urc"},{"type":"list","ordered":false,"spread":false,"position":{"start":{"line":111,"column":1},"end":{"line":116,"column":1}},"children":[{"type":"listItem","spread":true,"position":{"start":{"line":111,"column":1},"end":{"line":111,"column":1}},"children":[{"type":"strong","position":{"start":{"line":111,"column":1},"end":{"line":111,"column":1}},"children":[{"type":"text","value":"Heterogeneous consumers","position":{"start":{"line":111,"column":1},"end":{"line":111,"column":1}},"key":"CiKzggrg9e"}],"key":"g3oOvMZWOQ"},{"type":"text","value":": Casual vs regular fans","position":{"start":{"line":111,"column":1},"end":{"line":111,"column":1}},"key":"a8WCds2y9K"}],"key":"KyeKwONn4z"},{"type":"listItem","spread":true,"position":{"start":{"line":112,"column":1},"end":{"line":112,"column":1}},"children":[{"type":"strong","position":{"start":{"line":112,"column":1},"end":{"line":112,"column":1}},"children":[{"type":"text","value":"Dynamic model","position":{"start":{"line":112,"column":1},"end":{"line":112,"column":1}},"key":"A3dL2d0PCD"}],"key":"t6UFV2Y3BQ"},{"type":"text","value":": Repeated games, learning, habit formation","position":{"start":{"line":112,"column":1},"end":{"line":112,"column":1}},"key":"bC42NaQfSr"}],"key":"BspfXp7TkM"},{"type":"listItem","spread":true,"position":{"start":{"line":113,"column":1},"end":{"line":113,"column":1}},"children":[{"type":"strong","position":{"start":{"line":113,"column":1},"end":{"line":113,"column":1}},"children":[{"type":"text","value":"Substitution patterns","position":{"start":{"line":113,"column":1},"end":{"line":113,"column":1}},"key":"AGx18eXtsE"}],"key":"MrO4NPQdXa"},{"type":"text","value":": Pre-game bars, tailgating","position":{"start":{"line":113,"column":1},"end":{"line":113,"column":1}},"key":"z0HUkK5Yel"}],"key":"OcESGc0G8w"},{"type":"listItem","spread":true,"position":{"start":{"line":114,"column":1},"end":{"line":114,"column":1}},"children":[{"type":"strong","position":{"start":{"line":114,"column":1},"end":{"line":114,"column":1}},"children":[{"type":"text","value":"Spatial analysis","position":{"start":{"line":114,"column":1},"end":{"line":114,"column":1}},"key":"F3cp8uTW1w"}],"key":"wmIgzeP1UF"},{"type":"text","value":": Crime externalities by distance from stadium","position":{"start":{"line":114,"column":1},"end":{"line":114,"column":1}},"key":"zst2JqBncU"}],"key":"xuMG916shJ"},{"type":"listItem","spread":true,"position":{"start":{"line":115,"column":1},"end":{"line":116,"column":1}},"children":[{"type":"strong","position":{"start":{"line":115,"column":1},"end":{"line":115,"column":1}},"children":[{"type":"text","value":"Empirical validation","position":{"start":{"line":115,"column":1},"end":{"line":115,"column":1}},"key":"QlHMPOsWkk"}],"key":"ZwJV3HXRCu"},{"type":"text","value":": Natural experiments with policy changes","position":{"start":{"line":115,"column":1},"end":{"line":115,"column":1}},"key":"reRbkz3oai"}],"key":"wRUl9LKmqA"}],"key":"YQRn1knhoz"},{"type":"heading","depth":2,"position":{"start":{"line":117,"column":1},"end":{"line":117,"column":1}},"children":[{"type":"text","value":"Final Thought","position":{"start":{"line":117,"column":1},"end":{"line":117,"column":1}},"key":"cy0R38DjfF"}],"identifier":"final-thought","label":"Final Thought","html_id":"final-thought","implicit":true,"key":"SMI6rupvUw"},{"type":"paragraph","position":{"start":{"line":119,"column":1},"end":{"line":119,"column":1}},"children":[{"type":"text","value":"The key innovation is recognizing that ","position":{"start":{"line":119,"column":1},"end":{"line":119,"column":1}},"key":"h6rTQLogai"},{"type":"strong","position":{"start":{"line":119,"column":1},"end":{"line":119,"column":1}},"children":[{"type":"text","value":"monopolists internalize negative effects on their own customers","position":{"start":{"line":119,"column":1},"end":{"line":119,"column":1}},"key":"Astvq7kWtK"}],"key":"TU8y7Xzcdt"},{"type":"text","value":".","position":{"start":{"line":119,"column":1},"end":{"line":119,"column":1}},"key":"T5OISnUujI"}],"key":"DqRWEe6zKj"},{"type":"paragraph","position":{"start":{"line":121,"column":1},"end":{"line":121,"column":1}},"children":[{"type":"text","value":"This is why simple supply-demand models fail to predict stadium pricing - they miss the convex experience degradation costs that stadiums face.","position":{"start":{"line":121,"column":1},"end":{"line":121,"column":1}},"key":"rAhawgCD25"}],"key":"UN41uAiQs1"},{"type":"paragraph","position":{"start":{"line":123,"column":1},"end":{"line":123,"column":1}},"children":[{"type":"text","value":"For policy: Focus on ","position":{"start":{"line":123,"column":1},"end":{"line":123,"column":1}},"key":"RvIInU95Te"},{"type":"strong","position":{"start":{"line":123,"column":1},"end":{"line":123,"column":1}},"children":[{"type":"text","value":"true external costs","position":{"start":{"line":123,"column":1},"end":{"line":123,"column":1}},"key":"G9u0jA71lk"}],"key":"xDEWg8F0pf"},{"type":"text","value":" (crime, public health) that remain uninternalized. Current taxes cover only 27% of these costs.","position":{"start":{"line":123,"column":1},"end":{"line":123,"column":1}},"key":"oR1CfjeVS4"}],"key":"QxbfdUDZBp"},{"type":"paragraph","position":{"start":{"line":125,"column":1},"end":{"line":125,"column":1}},"children":[{"type":"strong","position":{"start":{"line":125,"column":1},"end":{"line":125,"column":1}},"children":[{"type":"text","value":"Optimal policy: ","position":{"start":{"line":125,"column":1},"end":{"line":125,"column":1}},"key":"y8KUNC8xfK"},{"type":"inlineMath","value":"2.91/beer Pigouvian tax, raising ","position":{"start":{"line":125,"column":1},"end":{"line":125,"column":1}},"html":"<span class=\"katex\"><span class=\"katex-mathml\"><math xmlns=\"http://www.w3.org/1998/Math/MathML\"><semantics><mrow><mn>2.91</mn><mi mathvariant=\"normal\">/</mi><mi>b</mi><mi>e</mi><mi>e</mi><mi>r</mi><mi>P</mi><mi>i</mi><mi>g</mi><mi>o</mi><mi>u</mi><mi>v</mi><mi>i</mi><mi>a</mi><mi>n</mi><mi>t</mi><mi>a</mi><mi>x</mi><mo separator=\"true\">,</mo><mi>r</mi><mi>a</mi><mi>i</mi><mi>s</mi><mi>i</mi><mi>n</mi><mi>g</mi></mrow><annotation encoding=\"application/x-tex\">2.91/beer Pigouvian tax, raising </annotation></semantics></math></span><span class=\"katex-html\" aria-hidden=\"true\"><span class=\"base\"><span class=\"strut\" style=\"height:1em;vertical-align:-0.25em;\"></span><span class=\"mord\">2.91/</span><span class=\"mord mathnormal\">b</span><span class=\"mord mathnormal\" style=\"margin-right:0.02778em;\">eer</span><span class=\"mord mathnormal\" style=\"margin-right:0.13889em;\">P</span><span class=\"mord mathnormal\">i</span><span class=\"mord mathnormal\" style=\"margin-right:0.03588em;\">g</span><span class=\"mord mathnormal\">o</span><span class=\"mord mathnormal\" style=\"margin-right:0.03588em;\">uv</span><span class=\"mord mathnormal\">ian</span><span class=\"mord mathnormal\">t</span><span class=\"mord mathnormal\">a</span><span class=\"mord mathnormal\">x</span><span class=\"mpunct\">,</span><span class=\"mspace\" style=\"margin-right:0.1667em;\"></span><span class=\"mord mathnormal\" style=\"margin-right:0.02778em;\">r</span><span class=\"mord mathnormal\">ai</span><span class=\"mord mathnormal\">s</span><span class=\"mord mathnormal\">in</span><span class=\"mord mathnormal\" style=\"margin-right:0.03588em;\">g</span></span></span></span>","key":"W4pHlFK9xt"},{"type":"text","value":"6.7M/season for NYC.","position":{"start":{"line":125,"column":1},"end":{"line":125,"column":1}},"key":"ddbA6vizJC"}],"key":"EM3qLr8SfG"}],"key":"e1fdYD3WbN"}],"key":"Uc4nFzPCM3"}],"key":"SOE23ioncH"},"references":{"cite":{"order":[],"data":{}}}}