{"version":2,"kind":"Article","sha256":"1e1e50dba0eb0b1c0edebc79d40cec42dde484e42bbee685ce37013184edbcb8","slug":"conclusion","location":"/conclusion.md","dependencies":[],"frontmatter":{"title":"Conclusions","content_includes_title":false,"authors":[{"nameParsed":{"literal":"Max Ghenis","given":"Max","family":"Ghenis"},"name":"Max Ghenis","email":"max@policyengine.org","id":"contributors-myst-generated-uid-0","corresponding":true}],"github":"https://github.com/maxghenis/yankee-stadium-beer-price-controls","keywords":["economics","sports","price controls","externalities","alcohol policy","pigouvian tax"],"copyright":"2025","numbering":{"title":{"offset":1}},"edit_url":"https://github.com/maxghenis/yankee-stadium-beer-price-controls/blob/master/docs/conclusion.md","exports":[{"format":"md","filename":"conclusion.md","url":"/conclusion-1da25d4cf40ba858213c13c9aa9aeb1e.md"}]},"mdast":{"type":"root","children":[{"type":"block","children":[{"type":"heading","depth":2,"position":{"start":{"line":3,"column":1},"end":{"line":3,"column":1}},"children":[{"type":"text","value":"Key Findings","position":{"start":{"line":3,"column":1},"end":{"line":3,"column":1}},"key":"M7lTfjqV6T"}],"identifier":"key-findings","label":"Key Findings","html_id":"key-findings","implicit":true,"key":"DmNAWj9ax7"},{"type":"heading","depth":3,"position":{"start":{"line":5,"column":1},"end":{"line":5,"column":1}},"children":[{"type":"text","value":"1. Observed Prices Are Profit-Maximizing","position":{"start":{"line":5,"column":1},"end":{"line":5,"column":1}},"key":"mzoPNASbMo"}],"identifier":"id-1-observed-prices-are-profit-maximizing","label":"1. Observed Prices Are Profit-Maximizing","html_id":"id-1-observed-prices-are-profit-maximizing","implicit":true,"key":"o1PniNLbZE"},{"type":"paragraph","position":{"start":{"line":7,"column":1},"end":{"line":7,"column":1}},"children":[{"type":"text","value":"Stadium beer at $12.50 is approximately profit-maximizing ($12.51 optimal) when accounting for:","position":{"start":{"line":7,"column":1},"end":{"line":7,"column":1}},"key":"c7NS0cgFty"}],"key":"V97iD6LfJf"},{"type":"list","ordered":false,"spread":false,"position":{"start":{"line":8,"column":1},"end":{"line":11,"column":1}},"children":[{"type":"listItem","spread":true,"position":{"start":{"line":8,"column":1},"end":{"line":8,"column":1}},"children":[{"type":"text","value":"Taxes ($1.18/beer)","position":{"start":{"line":8,"column":1},"end":{"line":8,"column":1}},"key":"AbN8sVmgxp"}],"key":"lB485m2LV9"},{"type":"listItem","spread":true,"position":{"start":{"line":9,"column":1},"end":{"line":9,"column":1}},"children":[{"type":"text","value":"Production costs ($2.00/beer)","position":{"start":{"line":9,"column":1},"end":{"line":9,"column":1}},"key":"ZPwX6axlJY"}],"key":"wDAM0QYo8M"},{"type":"listItem","spread":true,"position":{"start":{"line":10,"column":1},"end":{"line":11,"column":1}},"children":[{"type":"strong","position":{"start":{"line":10,"column":1},"end":{"line":10,"column":1}},"children":[{"type":"text","value":"Internalized costs","position":{"start":{"line":10,"column":1},"end":{"line":10,"column":1}},"key":"EpNSq84rtB"}],"key":"MofpemNVLg"},{"type":"text","value":" (varies by volume, C = 62.3(Q/1000)^2)","position":{"start":{"line":10,"column":1},"end":{"line":10,"column":1}},"key":"LgslqZQ2A3"}],"key":"WAWdJ6Ngo5"}],"key":"QpxIiyOIwu"},{"type":"heading","depth":3,"position":{"start":{"line":12,"column":1},"end":{"line":12,"column":1}},"children":[{"type":"text","value":"2. Stadiums Already Internalize Some Externalities","position":{"start":{"line":12,"column":1},"end":{"line":12,"column":1}},"key":"bvsBvRSnr5"}],"identifier":"id-2-stadiums-already-internalize-some-externalities","label":"2. Stadiums Already Internalize Some Externalities","html_id":"id-2-stadiums-already-internalize-some-externalities","implicit":true,"key":"RSJBubRUCS"},{"type":"paragraph","position":{"start":{"line":14,"column":1},"end":{"line":14,"column":1}},"children":[{"type":"text","value":"Crowd management, brand damage, and experience degradation are ","position":{"start":{"line":14,"column":1},"end":{"line":14,"column":1}},"key":"eObS4JN1FS"},{"type":"strong","position":{"start":{"line":14,"column":1},"end":{"line":14,"column":1}},"children":[{"type":"text","value":"already priced in","position":{"start":{"line":14,"column":1},"end":{"line":14,"column":1}},"key":"utmiHpp3NO"}],"key":"pHb3lkm6OT"},{"type":"text","value":":","position":{"start":{"line":14,"column":1},"end":{"line":14,"column":1}},"key":"cY9dI9IABm"}],"key":"x3PXahnimX"},{"type":"list","ordered":false,"spread":false,"position":{"start":{"line":15,"column":1},"end":{"line":18,"column":1}},"children":[{"type":"listItem","spread":true,"position":{"start":{"line":15,"column":1},"end":{"line":15,"column":1}},"children":[{"type":"text","value":"Convex cost function: ","position":{"start":{"line":15,"column":1},"end":{"line":15,"column":1}},"key":"MZLPGHnUvX"},{"type":"inlineMath","value":"C_{intern}(Q) = 62.3 \\cdot (Q/1000)^2","position":{"start":{"line":15,"column":1},"end":{"line":15,"column":1}},"html":"<span class=\"katex\"><span class=\"katex-mathml\"><math xmlns=\"http://www.w3.org/1998/Math/MathML\"><semantics><mrow><msub><mi>C</mi><mrow><mi>i</mi><mi>n</mi><mi>t</mi><mi>e</mi><mi>r</mi><mi>n</mi></mrow></msub><mo stretchy=\"false\">(</mo><mi>Q</mi><mo stretchy=\"false\">)</mo><mo>=</mo><mn>62.3</mn><mo>⋅</mo><mo stretchy=\"false\">(</mo><mi>Q</mi><mi mathvariant=\"normal\">/</mi><mn>1000</mn><msup><mo stretchy=\"false\">)</mo><mn>2</mn></msup></mrow><annotation encoding=\"application/x-tex\">C_{intern}(Q) = 62.3 \\cdot (Q/1000)^2</annotation></semantics></math></span><span class=\"katex-html\" aria-hidden=\"true\"><span class=\"base\"><span class=\"strut\" style=\"height:1em;vertical-align:-0.25em;\"></span><span class=\"mord\"><span class=\"mord mathnormal\" style=\"margin-right:0.07153em;\">C</span><span class=\"msupsub\"><span class=\"vlist-t vlist-t2\"><span class=\"vlist-r\"><span class=\"vlist\" style=\"height:0.3117em;\"><span style=\"top:-2.55em;margin-left:-0.0715em;margin-right:0.05em;\"><span class=\"pstrut\" style=\"height:2.7em;\"></span><span class=\"sizing reset-size6 size3 mtight\"><span class=\"mord mtight\"><span class=\"mord mathnormal mtight\">in</span><span class=\"mord mathnormal mtight\">t</span><span class=\"mord mathnormal mtight\" style=\"margin-right:0.02778em;\">er</span><span class=\"mord mathnormal mtight\">n</span></span></span></span></span><span class=\"vlist-s\">​</span></span><span class=\"vlist-r\"><span class=\"vlist\" style=\"height:0.15em;\"><span></span></span></span></span></span></span><span class=\"mopen\">(</span><span class=\"mord mathnormal\">Q</span><span class=\"mclose\">)</span><span class=\"mspace\" style=\"margin-right:0.2778em;\"></span><span class=\"mrel\">=</span><span class=\"mspace\" style=\"margin-right:0.2778em;\"></span></span><span class=\"base\"><span class=\"strut\" style=\"height:0.6444em;\"></span><span class=\"mord\">62.3</span><span class=\"mspace\" style=\"margin-right:0.2222em;\"></span><span class=\"mbin\">⋅</span><span class=\"mspace\" style=\"margin-right:0.2222em;\"></span></span><span class=\"base\"><span class=\"strut\" style=\"height:1.0641em;vertical-align:-0.25em;\"></span><span class=\"mopen\">(</span><span class=\"mord mathnormal\">Q</span><span class=\"mord\">/1000</span><span class=\"mclose\"><span class=\"mclose\">)</span><span class=\"msupsub\"><span class=\"vlist-t\"><span class=\"vlist-r\"><span class=\"vlist\" style=\"height:0.8141em;\"><span style=\"top:-3.063em;margin-right:0.05em;\"><span class=\"pstrut\" style=\"height:2.7em;\"></span><span class=\"sizing reset-size6 size3 mtight\"><span class=\"mord mtight\">2</span></span></span></span></span></span></span></span></span></span></span>","key":"pHiVNDEN1U"}],"key":"HMMLLs6EZH"},{"type":"listItem","spread":true,"position":{"start":{"line":16,"column":1},"end":{"line":16,"column":1}},"children":[{"type":"text","value":"At low prices ($5-7): Internalized costs become prohibitively high","position":{"start":{"line":16,"column":1},"end":{"line":16,"column":1}},"key":"sxodvee3H4"}],"key":"wULlUlKV0o"},{"type":"listItem","spread":true,"position":{"start":{"line":17,"column":1},"end":{"line":18,"column":1}},"children":[{"type":"text","value":"This explains why stadiums don’t sell cheap beer despite apparent profit potential","position":{"start":{"line":17,"column":1},"end":{"line":17,"column":1}},"key":"mFnzfaTn5v"}],"key":"ADKbgDW0FU"}],"key":"iLjcjdXoVY"},{"type":"heading","depth":3,"position":{"start":{"line":19,"column":1},"end":{"line":19,"column":1}},"children":[{"type":"text","value":"3. Significant External Costs Remain","position":{"start":{"line":19,"column":1},"end":{"line":19,"column":1}},"key":"xtRB3sqZW0"}],"identifier":"id-3-significant-external-costs-remain","label":"3. Significant External Costs Remain","html_id":"id-3-significant-external-costs-remain","implicit":true,"key":"DQf2H2fNQi"},{"type":"paragraph","position":{"start":{"line":21,"column":1},"end":{"line":21,"column":1}},"children":[{"type":"text","value":"Society bears ","position":{"start":{"line":21,"column":1},"end":{"line":21,"column":1}},"key":"J1LmujsMci"},{"type":"strong","position":{"start":{"line":21,"column":1},"end":{"line":21,"column":1}},"children":[{"type":"text","value":"$4.00/beer","position":{"start":{"line":21,"column":1},"end":{"line":21,"column":1}},"key":"LN9TPHpKM1"}],"key":"LgByZWgbit"},{"type":"text","value":" in external costs:","position":{"start":{"line":21,"column":1},"end":{"line":21,"column":1}},"key":"lFtOh75Nlo"}],"key":"MIhS1vvTD3"},{"type":"list","ordered":false,"spread":false,"position":{"start":{"line":22,"column":1},"end":{"line":24,"column":1}},"children":[{"type":"listItem","spread":true,"position":{"start":{"line":22,"column":1},"end":{"line":22,"column":1}},"children":[{"type":"text","value":"Crime & violence: $2.50","position":{"start":{"line":22,"column":1},"end":{"line":22,"column":1}},"key":"Wqd3Ij2F9z"}],"key":"uUjpn7V8Pj"},{"type":"listItem","spread":true,"position":{"start":{"line":23,"column":1},"end":{"line":24,"column":1}},"children":[{"type":"text","value":"Public health: $1.50","position":{"start":{"line":23,"column":1},"end":{"line":23,"column":1}},"key":"TnuZsWjl9M"}],"key":"p3787JOaRN"}],"key":"bOgXzzL1uV"},{"type":"paragraph","position":{"start":{"line":25,"column":1},"end":{"line":25,"column":1}},"children":[{"type":"text","value":"Current taxes ($1.18) cover only ","position":{"start":{"line":25,"column":1},"end":{"line":25,"column":1}},"key":"Umcl1ZpqgB"},{"type":"strong","position":{"start":{"line":25,"column":1},"end":{"line":25,"column":1}},"children":[{"type":"text","value":"30%","position":{"start":{"line":25,"column":1},"end":{"line":25,"column":1}},"key":"z1dqgzbN6V"}],"key":"AtaAaa9qkK"},{"type":"text","value":" of these costs.","position":{"start":{"line":25,"column":1},"end":{"line":25,"column":1}},"key":"ija6yzdLBq"}],"key":"naUh69Y2Yb"},{"type":"paragraph","position":{"start":{"line":27,"column":1},"end":{"line":27,"column":1}},"children":[{"type":"strong","position":{"start":{"line":27,"column":1},"end":{"line":27,"column":1}},"children":[{"type":"text","value":"Pigouvian tax gap: $2.82/beer","position":{"start":{"line":27,"column":1},"end":{"line":27,"column":1}},"key":"q4breoYokO"}],"key":"zrCy0DsASt"}],"key":"pS4cR1XBJy"},{"type":"heading","depth":3,"position":{"start":{"line":29,"column":1},"end":{"line":29,"column":1}},"children":[{"type":"text","value":"4. Price Ceiling ($7) Has Mixed Effects","position":{"start":{"line":29,"column":1},"end":{"line":29,"column":1}},"key":"q60m6Ct6Rw"}],"identifier":"id-4-price-ceiling-7-has-mixed-effects","label":"4. Price Ceiling ($7) Has Mixed Effects","html_id":"id-4-price-ceiling-7-has-mixed-effects","implicit":true,"key":"ba9ZPQ3HqN"},{"type":"paragraph","position":{"start":{"line":31,"column":1},"end":{"line":31,"column":1}},"children":[{"type":"strong","position":{"start":{"line":31,"column":1},"end":{"line":31,"column":1}},"children":[{"type":"text","value":"Pros:","position":{"start":{"line":31,"column":1},"end":{"line":31,"column":1}},"key":"Z6ndv0Xwt3"}],"key":"Qb09f1odJ3"}],"key":"VHPPUAoWK1"},{"type":"list","ordered":false,"spread":false,"position":{"start":{"line":32,"column":1},"end":{"line":34,"column":1}},"children":[{"type":"listItem","spread":true,"position":{"start":{"line":32,"column":1},"end":{"line":32,"column":1}},"children":[{"type":"text","value":"Consumer surplus: significant gains (+$5.3%)","position":{"start":{"line":32,"column":1},"end":{"line":32,"column":1}},"key":"AA3f3puSTR"}],"key":"HuYjwZi1si"},{"type":"listItem","spread":true,"position":{"start":{"line":33,"column":1},"end":{"line":34,"column":1}},"children":[{"type":"text","value":"More affordable access","position":{"start":{"line":33,"column":1},"end":{"line":33,"column":1}},"key":"JYHKYoRIyv"}],"key":"CULy7bdFkO"}],"key":"oC04Khp3Fr"},{"type":"paragraph","position":{"start":{"line":35,"column":1},"end":{"line":35,"column":1}},"children":[{"type":"strong","position":{"start":{"line":35,"column":1},"end":{"line":35,"column":1}},"children":[{"type":"text","value":"Cons:","position":{"start":{"line":35,"column":1},"end":{"line":35,"column":1}},"key":"Nj68q7f6QW"}],"key":"ZAiwLAh69F"}],"key":"sOmKIzC2si"},{"type":"list","ordered":false,"spread":false,"position":{"start":{"line":36,"column":1},"end":{"line":39,"column":1}},"children":[{"type":"listItem","spread":true,"position":{"start":{"line":36,"column":1},"end":{"line":36,"column":1}},"children":[{"type":"text","value":"Stadium profit: $-24.9M/season","position":{"start":{"line":36,"column":1},"end":{"line":36,"column":1}},"key":"gCPVKb6dv8"}],"key":"vxIk3EDzMr"},{"type":"listItem","spread":true,"position":{"start":{"line":37,"column":1},"end":{"line":37,"column":1}},"children":[{"type":"text","value":"Externality costs: increase (+$98.3%) due to higher consumption","position":{"start":{"line":37,"column":1},"end":{"line":37,"column":1}},"key":"UWXgYO9RFb"}],"key":"usalNEC81k"},{"type":"listItem","spread":true,"position":{"start":{"line":38,"column":1},"end":{"line":39,"column":1}},"children":[{"type":"text","value":"May face legal/constitutional challenges","position":{"start":{"line":38,"column":1},"end":{"line":38,"column":1}},"key":"XDqLFRt8Sb"}],"key":"b4xa2YLxHX"}],"key":"bIFrqC6GeT"},{"type":"paragraph","position":{"start":{"line":40,"column":1},"end":{"line":40,"column":1}},"children":[{"type":"strong","position":{"start":{"line":40,"column":1},"end":{"line":40,"column":1}},"children":[{"type":"text","value":"Net:","position":{"start":{"line":40,"column":1},"end":{"line":40,"column":1}},"key":"eRcfSjfYhh"}],"key":"yFSZ9gfFQ2"},{"type":"text","value":" Complex welfare trade-offs with distributional concerns.","position":{"start":{"line":40,"column":1},"end":{"line":40,"column":1}},"key":"zoJZTjtXIf"}],"key":"y4y8jpfTLt"},{"type":"heading","depth":3,"position":{"start":{"line":42,"column":1},"end":{"line":42,"column":1}},"children":[{"type":"text","value":"5. Pigouvian Tax is More Efficient","position":{"start":{"line":42,"column":1},"end":{"line":42,"column":1}},"key":"MYIRCuzfiR"}],"identifier":"id-5-pigouvian-tax-is-more-efficient","label":"5. Pigouvian Tax is More Efficient","html_id":"id-5-pigouvian-tax-is-more-efficient","implicit":true,"key":"LJ3QpEPXGL"},{"type":"paragraph","position":{"start":{"line":44,"column":1},"end":{"line":44,"column":1}},"children":[{"type":"text","value":"Adding $2.82/beer tax:","position":{"start":{"line":44,"column":1},"end":{"line":44,"column":1}},"key":"VqnMPmKV0V"}],"key":"BYcCMzAmb2"},{"type":"list","ordered":false,"spread":false,"position":{"start":{"line":45,"column":1},"end":{"line":50,"column":1}},"children":[{"type":"listItem","spread":true,"position":{"start":{"line":45,"column":1},"end":{"line":45,"column":1}},"children":[{"type":"text","value":"✓ Internalizes external costs","position":{"start":{"line":45,"column":1},"end":{"line":45,"column":1}},"key":"asTUIQlSI4"}],"key":"y71cI7sbPP"},{"type":"listItem","spread":true,"position":{"start":{"line":46,"column":1},"end":{"line":46,"column":1}},"children":[{"type":"text","value":"✓ Raises $10.6M/year for affected communities","position":{"start":{"line":46,"column":1},"end":{"line":46,"column":1}},"key":"uh0RCkxpEB"}],"key":"kkDR6e1BH3"},{"type":"listItem","spread":true,"position":{"start":{"line":47,"column":1},"end":{"line":47,"column":1}},"children":[{"type":"text","value":"✓ Reduces consumption to optimal level","position":{"start":{"line":47,"column":1},"end":{"line":47,"column":1}},"key":"BL4mPaw25z"}],"key":"x03yAcrDbj"},{"type":"listItem","spread":true,"position":{"start":{"line":48,"column":1},"end":{"line":48,"column":1}},"children":[{"type":"text","value":"✓ No deadweight loss (price = social MC)","position":{"start":{"line":48,"column":1},"end":{"line":48,"column":1}},"key":"cB5FVvhecE"}],"key":"O3qokB5MLv"},{"type":"listItem","spread":true,"position":{"start":{"line":49,"column":1},"end":{"line":50,"column":1}},"children":[{"type":"text","value":"✓ Economically efficient","position":{"start":{"line":49,"column":1},"end":{"line":49,"column":1}},"key":"HbBzPNwamZ"}],"key":"MD6faWupnb"}],"key":"RSKv3xbIlo"},{"type":"paragraph","position":{"start":{"line":51,"column":1},"end":{"line":51,"column":1}},"children":[{"type":"strong","position":{"start":{"line":51,"column":1},"end":{"line":51,"column":1}},"children":[{"type":"text","value":"Recommended policy","position":{"start":{"line":51,"column":1},"end":{"line":51,"column":1}},"key":"WFfbu9EHD3"}],"key":"zjKzNk4kcS"},{"type":"text","value":": Pigouvian tax over price controls.","position":{"start":{"line":51,"column":1},"end":{"line":51,"column":1}},"key":"p188ALfeAv"}],"key":"pPNrRRN5IX"},{"type":"heading","depth":2,"position":{"start":{"line":53,"column":1},"end":{"line":53,"column":1}},"children":[{"type":"text","value":"Policy Recommendations","position":{"start":{"line":53,"column":1},"end":{"line":53,"column":1}},"key":"jaY7ZoLcqu"}],"identifier":"policy-recommendations","label":"Policy Recommendations","html_id":"policy-recommendations","implicit":true,"key":"k6jmTQMWM8"},{"type":"heading","depth":3,"position":{"start":{"line":55,"column":1},"end":{"line":55,"column":1}},"children":[{"type":"text","value":"Recommended: Pigouvian Tax","position":{"start":{"line":55,"column":1},"end":{"line":55,"column":1}},"key":"HtksBMiExr"}],"identifier":"recommended-pigouvian-tax","label":"Recommended: Pigouvian Tax","html_id":"recommended-pigouvian-tax","implicit":true,"key":"sVNOxrewfC"},{"type":"paragraph","position":{"start":{"line":57,"column":1},"end":{"line":57,"column":1}},"children":[{"type":"strong","position":{"start":{"line":57,"column":1},"end":{"line":57,"column":1}},"children":[{"type":"text","value":"Implement $2.82/beer additional tax on stadium alcohol","position":{"start":{"line":57,"column":1},"end":{"line":57,"column":1}},"key":"tbQhbgLbnN"}],"key":"aZpliKb01x"}],"key":"KaRJovqRZv"},{"type":"list","ordered":false,"spread":false,"position":{"start":{"line":59,"column":1},"end":{"line":63,"column":1}},"children":[{"type":"listItem","spread":true,"position":{"start":{"line":59,"column":1},"end":{"line":59,"column":1}},"children":[{"type":"text","value":"Consumer price: $12.51 → $15.33","position":{"start":{"line":59,"column":1},"end":{"line":59,"column":1}},"key":"ZQ6s1bhrYF"}],"key":"I9jrCBKFNw"},{"type":"listItem","spread":true,"position":{"start":{"line":60,"column":1},"end":{"line":60,"column":1}},"children":[{"type":"text","value":"Consumption: reduces to optimal level","position":{"start":{"line":60,"column":1},"end":{"line":60,"column":1}},"key":"fLC1JDgskp"}],"key":"akOpfKKjdR"},{"type":"listItem","spread":true,"position":{"start":{"line":61,"column":1},"end":{"line":61,"column":1}},"children":[{"type":"text","value":"Revenue: $10.6M/year","position":{"start":{"line":61,"column":1},"end":{"line":61,"column":1}},"key":"kGb9eoQ2oO"}],"key":"td8LrLgtnd"},{"type":"listItem","spread":true,"position":{"start":{"line":62,"column":1},"end":{"line":63,"column":1}},"children":[{"type":"text","value":"Allocate to Bronx community, public health, police","position":{"start":{"line":62,"column":1},"end":{"line":62,"column":1}},"key":"uoA8TMqmye"}],"key":"rZqPIShTpT"}],"key":"zpaywePXGS"},{"type":"heading","depth":3,"position":{"start":{"line":64,"column":1},"end":{"line":64,"column":1}},"children":[{"type":"text","value":"Alternative: Moderate Hybrid","position":{"start":{"line":64,"column":1},"end":{"line":64,"column":1}},"key":"F5RQKK0eHm"}],"identifier":"alternative-moderate-hybrid","label":"Alternative: Moderate Hybrid","html_id":"alternative-moderate-hybrid","implicit":true,"key":"amOUXbgDJv"},{"type":"paragraph","position":{"start":{"line":66,"column":1},"end":{"line":66,"column":1}},"children":[{"type":"strong","position":{"start":{"line":66,"column":1},"end":{"line":66,"column":1}},"children":[{"type":"text","value":"If political constraints:","position":{"start":{"line":66,"column":1},"end":{"line":66,"column":1}},"key":"AFo5zzToBJ"}],"key":"L5wqXVqXOp"}],"key":"Qpr5po6IMt"},{"type":"list","ordered":false,"spread":false,"position":{"start":{"line":67,"column":1},"end":{"line":70,"column":1}},"children":[{"type":"listItem","spread":true,"position":{"start":{"line":67,"column":1},"end":{"line":67,"column":1}},"children":[{"type":"text","value":"Moderate tax (+$1.50/beer)","position":{"start":{"line":67,"column":1},"end":{"line":67,"column":1}},"key":"LpYU8TsnsL"}],"key":"Yp9ySLXtSf"},{"type":"listItem","spread":true,"position":{"start":{"line":68,"column":1},"end":{"line":68,"column":1}},"children":[{"type":"text","value":"Earlier sale cutoff (6th inning instead of 7th)","position":{"start":{"line":68,"column":1},"end":{"line":68,"column":1}},"key":"buNYEX45SW"}],"key":"F4lCGE05Lr"},{"type":"listItem","spread":true,"position":{"start":{"line":69,"column":1},"end":{"line":70,"column":1}},"children":[{"type":"text","value":"Purchase limits (2 beers per transaction)","position":{"start":{"line":69,"column":1},"end":{"line":69,"column":1}},"key":"UN5XFMNZT2"}],"key":"Pk2rSpG7R3"}],"key":"f609x7LxfP"},{"type":"heading","depth":3,"position":{"start":{"line":71,"column":1},"end":{"line":71,"column":1}},"children":[{"type":"text","value":"Not Recommended: Price Ceiling","position":{"start":{"line":71,"column":1},"end":{"line":71,"column":1}},"key":"dNgUNnzYXE"}],"identifier":"not-recommended-price-ceiling","label":"Not Recommended: Price Ceiling","html_id":"not-recommended-price-ceiling","implicit":true,"key":"LXLMamRBmy"},{"type":"list","ordered":false,"spread":false,"position":{"start":{"line":73,"column":1},"end":{"line":77,"column":1}},"children":[{"type":"listItem","spread":true,"position":{"start":{"line":73,"column":1},"end":{"line":73,"column":1}},"children":[{"type":"text","value":"Large stadium revenue loss","position":{"start":{"line":73,"column":1},"end":{"line":73,"column":1}},"key":"CQziGXUX7w"}],"key":"cddzvCEwHu"},{"type":"listItem","spread":true,"position":{"start":{"line":74,"column":1},"end":{"line":74,"column":1}},"children":[{"type":"text","value":"Increases externalities","position":{"start":{"line":74,"column":1},"end":{"line":74,"column":1}},"key":"HWzRcIRYOL"}],"key":"flStOng44h"},{"type":"listItem","spread":true,"position":{"start":{"line":75,"column":1},"end":{"line":75,"column":1}},"children":[{"type":"text","value":"Potential legal challenges","position":{"start":{"line":75,"column":1},"end":{"line":75,"column":1}},"key":"bjv8V5UFxi"}],"key":"kDJZyI6E3T"},{"type":"listItem","spread":true,"position":{"start":{"line":76,"column":1},"end":{"line":77,"column":1}},"children":[{"type":"text","value":"Less efficient than taxation","position":{"start":{"line":76,"column":1},"end":{"line":76,"column":1}},"key":"QhgMdAn9sZ"}],"key":"MUocWqxxnG"}],"key":"FfiCNsoWWZ"},{"type":"heading","depth":2,"position":{"start":{"line":78,"column":1},"end":{"line":78,"column":1}},"children":[{"type":"text","value":"Broader Implications","position":{"start":{"line":78,"column":1},"end":{"line":78,"column":1}},"key":"YSBP0i9e7m"}],"identifier":"broader-implications","label":"Broader Implications","html_id":"broader-implications","implicit":true,"key":"dhQ2M4mo4P"},{"type":"heading","depth":3,"position":{"start":{"line":80,"column":1},"end":{"line":80,"column":1}},"children":[{"type":"text","value":"For Other Stadiums","position":{"start":{"line":80,"column":1},"end":{"line":80,"column":1}},"key":"y7dweOW7aZ"}],"identifier":"for-other-stadiums","label":"For Other Stadiums","html_id":"for-other-stadiums","implicit":true,"key":"tZdMleHMrQ"},{"type":"paragraph","position":{"start":{"line":82,"column":1},"end":{"line":82,"column":1}},"children":[{"type":"text","value":"This framework applies to all sports venues:","position":{"start":{"line":82,"column":1},"end":{"line":82,"column":1}},"key":"vxmGBROjU9"}],"key":"YkeyYEmjJr"},{"type":"list","ordered":false,"spread":false,"position":{"start":{"line":83,"column":1},"end":{"line":86,"column":1}},"children":[{"type":"listItem","spread":true,"position":{"start":{"line":83,"column":1},"end":{"line":83,"column":1}},"children":[{"type":"text","value":"NFL, NBA, NHL stadiums face similar trade-offs","position":{"start":{"line":83,"column":1},"end":{"line":83,"column":1}},"key":"zs4Jt1UqQv"}],"key":"X0RwhpGOpW"},{"type":"listItem","spread":true,"position":{"start":{"line":84,"column":1},"end":{"line":84,"column":1}},"children":[{"type":"text","value":"Internalized vs external costs distinction is general","position":{"start":{"line":84,"column":1},"end":{"line":84,"column":1}},"key":"Q6PFiH4s91"}],"key":"FIKPMbLP60"},{"type":"listItem","spread":true,"position":{"start":{"line":85,"column":1},"end":{"line":86,"column":1}},"children":[{"type":"text","value":"Optimal taxation varies by local externality levels","position":{"start":{"line":85,"column":1},"end":{"line":85,"column":1}},"key":"o3tgXFiFjY"}],"key":"Uls88aC6i8"}],"key":"t9xZpEtPlX"},{"type":"heading","depth":3,"position":{"start":{"line":87,"column":1},"end":{"line":87,"column":1}},"children":[{"type":"text","value":"For Alcohol Policy","position":{"start":{"line":87,"column":1},"end":{"line":87,"column":1}},"key":"HZAz7QRGQ8"}],"identifier":"for-alcohol-policy","label":"For Alcohol Policy","html_id":"for-alcohol-policy","implicit":true,"key":"nQ8kVeeooX"},{"type":"paragraph","position":{"start":{"line":89,"column":1},"end":{"line":89,"column":1}},"children":[{"type":"strong","position":{"start":{"line":89,"column":1},"end":{"line":89,"column":1}},"children":[{"type":"text","value":"General principle","position":{"start":{"line":89,"column":1},"end":{"line":89,"column":1}},"key":"M1Xt6vk4RW"}],"key":"ScY86Yz2NY"},{"type":"text","value":": Distinguish internalized from external costs.","position":{"start":{"line":89,"column":1},"end":{"line":89,"column":1}},"key":"TVWd8UOynB"}],"key":"Y8KCQRhMlP"},{"type":"paragraph","position":{"start":{"line":91,"column":1},"end":{"line":91,"column":1}},"children":[{"type":"text","value":"Monopolists (stadiums, bars, restaurants) internalize negative effects on their own customers.","position":{"start":{"line":91,"column":1},"end":{"line":91,"column":1}},"key":"Nm1XDEp8rC"}],"key":"JPmocESAL2"},{"type":"paragraph","position":{"start":{"line":93,"column":1},"end":{"line":93,"column":1}},"children":[{"type":"text","value":"Policy should target ","position":{"start":{"line":93,"column":1},"end":{"line":93,"column":1}},"key":"f3MnxRX3YI"},{"type":"strong","position":{"start":{"line":93,"column":1},"end":{"line":93,"column":1}},"children":[{"type":"text","value":"true external costs","position":{"start":{"line":93,"column":1},"end":{"line":93,"column":1}},"key":"ccT0HbvJf6"}],"key":"m1ozbi0RfQ"},{"type":"text","value":" (non-customers, public goods).","position":{"start":{"line":93,"column":1},"end":{"line":93,"column":1}},"key":"LTiaDdCZJQ"}],"key":"tAkZlMJbaQ"},{"type":"heading","depth":3,"position":{"start":{"line":95,"column":1},"end":{"line":95,"column":1}},"children":[{"type":"text","value":"For Price Control Theory","position":{"start":{"line":95,"column":1},"end":{"line":95,"column":1}},"key":"roqnLMTN6c"}],"identifier":"for-price-control-theory","label":"For Price Control Theory","html_id":"for-price-control-theory","implicit":true,"key":"aiwSqrUmTe"},{"type":"paragraph","position":{"start":{"line":97,"column":1},"end":{"line":97,"column":1}},"children":[{"type":"strong","position":{"start":{"line":97,"column":1},"end":{"line":97,"column":1}},"children":[{"type":"text","value":"Important insight","position":{"start":{"line":97,"column":1},"end":{"line":97,"column":1}},"key":"HreAvUn73I"}],"key":"LBiNpS0nfD"},{"type":"text","value":": Observed prices may reflect internalized externalities, not just production costs.","position":{"start":{"line":97,"column":1},"end":{"line":97,"column":1}},"key":"syB4yuvinx"}],"key":"fAo8ac3Xrq"},{"type":"paragraph","position":{"start":{"line":99,"column":1},"end":{"line":99,"column":1}},"children":[{"type":"text","value":"Standard models that ignore firm’s internalization of customer experience effects will mis-predict optimal prices.","position":{"start":{"line":99,"column":1},"end":{"line":99,"column":1}},"key":"xpYKriSEUX"}],"key":"RGYiVxctOx"},{"type":"heading","depth":2,"position":{"start":{"line":101,"column":1},"end":{"line":101,"column":1}},"children":[{"type":"text","value":"Limitations","position":{"start":{"line":101,"column":1},"end":{"line":101,"column":1}},"key":"SVrE9199Bt"}],"identifier":"limitations","label":"Limitations","html_id":"limitations","implicit":true,"key":"OEZUuNQ7GR"},{"type":"list","ordered":true,"start":1,"spread":false,"position":{"start":{"line":103,"column":1},"end":{"line":108,"column":1}},"children":[{"type":"listItem","spread":true,"position":{"start":{"line":103,"column":1},"end":{"line":103,"column":1}},"children":[{"type":"strong","position":{"start":{"line":103,"column":1},"end":{"line":103,"column":1}},"children":[{"type":"text","value":"Static model","position":{"start":{"line":103,"column":1},"end":{"line":103,"column":1}},"key":"rUWRpyLIGO"}],"key":"NnSPmMFtQh"},{"type":"text","value":": Doesn’t capture long-run effects (season tickets, loyalty)","position":{"start":{"line":103,"column":1},"end":{"line":103,"column":1}},"key":"XaMDHv2HQW"}],"key":"cZT92Otqlt"},{"type":"listItem","spread":true,"position":{"start":{"line":104,"column":1},"end":{"line":104,"column":1}},"children":[{"type":"strong","position":{"start":{"line":104,"column":1},"end":{"line":104,"column":1}},"children":[{"type":"text","value":"Single representative consumer","position":{"start":{"line":104,"column":1},"end":{"line":104,"column":1}},"key":"oPfQLaDhNt"}],"key":"GAs9GQwdXP"},{"type":"text","value":": Ignores heterogeneity","position":{"start":{"line":104,"column":1},"end":{"line":104,"column":1}},"key":"O47BrUl0BH"}],"key":"VjeU7ty3re"},{"type":"listItem","spread":true,"position":{"start":{"line":105,"column":1},"end":{"line":105,"column":1}},"children":[{"type":"strong","position":{"start":{"line":105,"column":1},"end":{"line":105,"column":1}},"children":[{"type":"text","value":"No substitution","position":{"start":{"line":105,"column":1},"end":{"line":105,"column":1}},"key":"U5CHZhDldP"}],"key":"yit29eoKeA"},{"type":"text","value":": Doesn’t model pre-game drinking or smuggling","position":{"start":{"line":105,"column":1},"end":{"line":105,"column":1}},"key":"y6QdoaNSbJ"}],"key":"TmZucYIc6g"},{"type":"listItem","spread":true,"position":{"start":{"line":106,"column":1},"end":{"line":106,"column":1}},"children":[{"type":"strong","position":{"start":{"line":106,"column":1},"end":{"line":106,"column":1}},"children":[{"type":"text","value":"Partial equilibrium","position":{"start":{"line":106,"column":1},"end":{"line":106,"column":1}},"key":"KkPpTteCDt"}],"key":"ttabAWDQTX"},{"type":"text","value":": No competition from other entertainment","position":{"start":{"line":106,"column":1},"end":{"line":106,"column":1}},"key":"Kwn5bZX2KG"}],"key":"vsCBBhjwSI"},{"type":"listItem","spread":true,"position":{"start":{"line":107,"column":1},"end":{"line":108,"column":1}},"children":[{"type":"strong","position":{"start":{"line":107,"column":1},"end":{"line":107,"column":1}},"children":[{"type":"text","value":"Perfect enforcement","position":{"start":{"line":107,"column":1},"end":{"line":107,"column":1}},"key":"aPP0S547CO"}],"key":"aZwj6oKj3t"},{"type":"text","value":": Assumes price controls fully enforced","position":{"start":{"line":107,"column":1},"end":{"line":107,"column":1}},"key":"tvyCGCPK7V"}],"key":"IMTT8wDem8"}],"key":"JuZizsgwP3"},{"type":"heading","depth":2,"position":{"start":{"line":109,"column":1},"end":{"line":109,"column":1}},"children":[{"type":"text","value":"Future Research","position":{"start":{"line":109,"column":1},"end":{"line":109,"column":1}},"key":"vLyC2hKA14"}],"identifier":"future-research","label":"Future Research","html_id":"future-research","implicit":true,"key":"K6EvD4WFY6"},{"type":"list","ordered":false,"spread":false,"position":{"start":{"line":111,"column":1},"end":{"line":118,"column":1}},"children":[{"type":"listItem","spread":true,"position":{"start":{"line":111,"column":1},"end":{"line":111,"column":1}},"children":[{"type":"strong","position":{"start":{"line":111,"column":1},"end":{"line":111,"column":1}},"children":[{"type":"text","value":"Rowdiness Feedback Loop","position":{"start":{"line":111,"column":1},"end":{"line":111,"column":1}},"key":"zutssZtDFi"}],"key":"NxZ4XJjf8w"},{"type":"text","value":": Explicitly model the negative utility of non-drinkers from high aggregate beer consumption.","position":{"start":{"line":111,"column":1},"end":{"line":111,"column":1}},"key":"mnaZYErQNZ"}],"key":"x7BlOX8OX7"},{"type":"listItem","spread":true,"position":{"start":{"line":112,"column":1},"end":{"line":112,"column":1}},"children":[{"type":"strong","position":{"start":{"line":112,"column":1},"end":{"line":112,"column":1}},"children":[{"type":"text","value":"Convex Externalities","position":{"start":{"line":112,"column":1},"end":{"line":112,"column":1}},"key":"Key7UegBXq"}],"key":"VwhjlQf5Tp"},{"type":"text","value":": Investigate how social externalities (crime, health) might increase non-linearly with consumption.","position":{"start":{"line":112,"column":1},"end":{"line":112,"column":1}},"key":"sUkITVl4QZ"}],"key":"YBrR97wPgg"},{"type":"listItem","spread":true,"position":{"start":{"line":113,"column":1},"end":{"line":113,"column":1}},"children":[{"type":"strong","position":{"start":{"line":113,"column":1},"end":{"line":113,"column":1}},"children":[{"type":"text","value":"Heterogeneous consumers","position":{"start":{"line":113,"column":1},"end":{"line":113,"column":1}},"key":"oY7d5xbhJ4"}],"key":"SjvZtLDT1z"},{"type":"text","value":": Deeper dive into casual vs regular fans, potentially expanding consumer types.","position":{"start":{"line":113,"column":1},"end":{"line":113,"column":1}},"key":"ZFCwXinX60"}],"key":"pcgst11PXt"},{"type":"listItem","spread":true,"position":{"start":{"line":114,"column":1},"end":{"line":114,"column":1}},"children":[{"type":"strong","position":{"start":{"line":114,"column":1},"end":{"line":114,"column":1}},"children":[{"type":"text","value":"Dynamic model","position":{"start":{"line":114,"column":1},"end":{"line":114,"column":1}},"key":"wCcCLRjHT0"}],"key":"diLMU9Ptay"},{"type":"text","value":": Repeated games, learning, habit formation.","position":{"start":{"line":114,"column":1},"end":{"line":114,"column":1}},"key":"d6p8tmfUJH"}],"key":"bdjkQcxe56"},{"type":"listItem","spread":true,"position":{"start":{"line":115,"column":1},"end":{"line":115,"column":1}},"children":[{"type":"strong","position":{"start":{"line":115,"column":1},"end":{"line":115,"column":1}},"children":[{"type":"text","value":"Substitution patterns","position":{"start":{"line":115,"column":1},"end":{"line":115,"column":1}},"key":"ptSGD1y5C7"}],"key":"LjCnfZF3cl"},{"type":"text","value":": Pre-game bars, tailgating.","position":{"start":{"line":115,"column":1},"end":{"line":115,"column":1}},"key":"njPUEKnzUh"}],"key":"E1fyMDuCrR"},{"type":"listItem","spread":true,"position":{"start":{"line":116,"column":1},"end":{"line":116,"column":1}},"children":[{"type":"strong","position":{"start":{"line":116,"column":1},"end":{"line":116,"column":1}},"children":[{"type":"text","value":"Spatial analysis","position":{"start":{"line":116,"column":1},"end":{"line":116,"column":1}},"key":"a4nQ0NDXmt"}],"key":"Bl3bJWEf4c"},{"type":"text","value":": Crime externalities by distance from stadium.","position":{"start":{"line":116,"column":1},"end":{"line":116,"column":1}},"key":"gLKIRfJp3D"}],"key":"ukkoITRQ3t"},{"type":"listItem","spread":true,"position":{"start":{"line":117,"column":1},"end":{"line":118,"column":1}},"children":[{"type":"strong","position":{"start":{"line":117,"column":1},"end":{"line":117,"column":1}},"children":[{"type":"text","value":"Empirical validation","position":{"start":{"line":117,"column":1},"end":{"line":117,"column":1}},"key":"XF2ZgV9ihK"}],"key":"iGi6hFB2Ub"},{"type":"text","value":": Natural experiments with policy changes.","position":{"start":{"line":117,"column":1},"end":{"line":117,"column":1}},"key":"MJMZibH3A3"}],"key":"BxUwpYtAKe"}],"key":"FUVwRc6kk1"},{"type":"heading","depth":2,"position":{"start":{"line":119,"column":1},"end":{"line":119,"column":1}},"children":[{"type":"text","value":"Final Thought","position":{"start":{"line":119,"column":1},"end":{"line":119,"column":1}},"key":"pgJ3d7B6LP"}],"identifier":"final-thought","label":"Final Thought","html_id":"final-thought","implicit":true,"key":"ZL8bseGsge"},{"type":"paragraph","position":{"start":{"line":121,"column":1},"end":{"line":121,"column":1}},"children":[{"type":"text","value":"The key innovation is recognizing that ","position":{"start":{"line":121,"column":1},"end":{"line":121,"column":1}},"key":"OpTh2lwWTe"},{"type":"strong","position":{"start":{"line":121,"column":1},"end":{"line":121,"column":1}},"children":[{"type":"text","value":"monopolists internalize negative effects on their own customers","position":{"start":{"line":121,"column":1},"end":{"line":121,"column":1}},"key":"vN9IjqP3tL"}],"key":"vYAPmpVCQb"},{"type":"text","value":".","position":{"start":{"line":121,"column":1},"end":{"line":121,"column":1}},"key":"plgwuWclXN"}],"key":"vDGKuOf4ne"},{"type":"paragraph","position":{"start":{"line":123,"column":1},"end":{"line":123,"column":1}},"children":[{"type":"text","value":"This is why simple supply-demand models fail to predict stadium pricing - they miss the convex experience degradation costs that stadiums face.","position":{"start":{"line":123,"column":1},"end":{"line":123,"column":1}},"key":"bToag3ZWft"}],"key":"eBbSSacaap"},{"type":"paragraph","position":{"start":{"line":125,"column":1},"end":{"line":125,"column":1}},"children":[{"type":"text","value":"For policy: Focus on ","position":{"start":{"line":125,"column":1},"end":{"line":125,"column":1}},"key":"VnoJV8CKGt"},{"type":"strong","position":{"start":{"line":125,"column":1},"end":{"line":125,"column":1}},"children":[{"type":"text","value":"true external costs","position":{"start":{"line":125,"column":1},"end":{"line":125,"column":1}},"key":"epLNquWGdq"}],"key":"jzCuDotNBd"},{"type":"text","value":" (crime, public health) that remain uninternalized. Current taxes cover only 30% of these costs.","position":{"start":{"line":125,"column":1},"end":{"line":125,"column":1}},"key":"iZItK9RII4"}],"key":"S734yO27w1"},{"type":"paragraph","position":{"start":{"line":127,"column":1},"end":{"line":127,"column":1}},"children":[{"type":"strong","position":{"start":{"line":127,"column":1},"end":{"line":127,"column":1}},"children":[{"type":"text","value":"Optimal policy: $2.82/beer Pigouvian tax, raising $10.6M/year for NYC.","position":{"start":{"line":127,"column":1},"end":{"line":127,"column":1}},"key":"QJTrWK92zu"}],"key":"peBBRE4pza"}],"key":"lPHYrR9vQf"}],"key":"su9BKZjcEi"}],"key":"Pzn93Ky8WT"},"references":{"cite":{"order":[],"data":{}}}}